alibabacloud_filedetect/Config.py
alibabacloud_filedetect/Decompress.py
alibabacloud_filedetect/DetectResult.py
alibabacloud_filedetect/ERR_CODE.py
alibabacloud_filedetect/IDetectResultCallback.py
alibabacloud_filedetect/MiniThreadPool.py
alibabacloud_filedetect/OpenAPIDetector.py
alibabacloud_filedetect/ScanTask.py
alibabacloud_filedetect/__init__.py
alibabacloud_filedetect-1.1.2.dist-info/LICENSE
alibabacloud_filedetect-1.1.2.dist-info/METADATA
alibabacloud_filedetect-1.1.2.dist-info/WHEEL
alibabacloud_filedetect-1.1.2.dist-info/top_level.txt
alibabacloud_filedetect-1.1.2.dist-info/RECORD
